access/__init__.py
access/decorators.py
access/factories.py
access/http.py
access/requirements.py
access/views.py
access/tests/__init__.py
access/tests/test_decorators.py
access/tests/test_requirements.py
access/tests/test_views.py
access/tests/utils.py
django_access_tools-2.0.0.dist-info/LICENSE
django_access_tools-2.0.0.dist-info/METADATA
django_access_tools-2.0.0.dist-info/WHEEL
django_access_tools-2.0.0.dist-info/top_level.txt
django_access_tools-2.0.0.dist-info/RECORD
