Metadata-Version: 2.1
Name: django-access-tools
Version: 2.0.0
Summary: An abstract access manager for Django.
Home-page: http://antonagestam.github.io/django-access-tools
Author: Anton Agestam
Author-email: msn@antonagestam.se
License: UNKNOWN
Platform: UNKNOWN
Classifier: Framework :: Django
Classifier: Intended Audience :: Developers
Classifier: Operating System :: OS Independent
Classifier: Topic :: Software Development
Classifier: Programming Language :: Python :: 3.4
Classifier: Programming Language :: Python :: 3.5
Classifier: Programming Language :: Python :: 3.6
Classifier: Programming Language :: Python :: 3.7
Requires-Dist: Django (>=2.0)
